remixtree/__init__.py
remixtree/api.py
remixtree/cli.py
remixtree/main.py
remixtree/node.py
remixtree/tree_builder.py
remixtree-0.1.17.dist-info/licenses/LICENSE
remixtree-0.1.17.dist-info/METADATA
remixtree-0.1.17.dist-info/WHEEL
remixtree-0.1.17.dist-info/entry_points.txt
remixtree-0.1.17.dist-info/top_level.txt
remixtree-0.1.17.dist-info/RECORD
