Metadata-Version: 2.4
Name: remixtree
Version: 0.1.17
Summary: remake scratch's remix tree feature #BringBackRemixTrees
Author-email: Alastrantia <example@email.com>
License: MIT
Project-URL: Homepage, https://github.com/Alastrantia/scratch-remixtree
Project-URL: BugTracker, https://github.com/Alastrantia/scratch-remixtree/issues
Classifier: Programming Language :: Python :: 3
Classifier: License :: OSI Approved :: MIT License
Classifier: Operating System :: OS Independent
Classifier: Topic :: Software Development :: Build Tools
Classifier: Topic :: Education
Requires-Python: >=3.9
License-File: LICENSE
Requires-Dist: aiohttp
Requires-Dist: rich
Dynamic: license-file
